respy/__init__.py
respy/act.py
respy/respy.py
respy-0.1.1.dist-info/LICENSE
respy-0.1.1.dist-info/METADATA
respy-0.1.1.dist-info/WHEEL
respy-0.1.1.dist-info/top_level.txt
respy-0.1.1.dist-info/RECORD
