Metadata-Version: 2.1
Name: respy
Version: 0.1.1
Summary: A set of function for analysis of single belt respiration measurements
Author-email: Finn Upham <finn.upham@gmail.com>
Project-URL: Homepage, https://github.com/finn42/respy_demo
Classifier: Programming Language :: Python :: 3
Classifier: License :: OSI Approved :: MIT License
Classifier: Operating System :: OS Independent
Requires-Python: >=3.7
License-File: LICENSE
